<?xml version="1.0" encoding="utf-8"?>
<ArrayOfEngineer xmlns:xsi="http://www.w3.org/2001/XMLSchema-instance" xmlns:xsd="http://www.w3.org/2001/XMLSchema">
  <Engineer>
    <Id>303892709</Id>
    <Name>Sara Borgen</Name>
    <Email>sara.borgen@emailgame.com</Email>
    <Level>Expert</Level>
    <Cost>267</Cost>
  </Engineer>
  <Engineer>
    <Id>294545391</Id>
    <Name>Naama Leah Radonsky</Name>
    <Email>naama.radonsky@emailgame.com</Email>
    <Level>Advanced</Level>
    <Cost>256</Cost>
  </Engineer>
  <Engineer>
    <Id>236113762</Id>
    <Name>Ester Dray</Name>
    <Email>ester.dray@emailgame.com</Email>
    <Level>AdvancedBeginner</Level>
    <Cost>121</Cost>
  </Engineer>
  <Engineer>
    <Id>365055538</Id>
    <Name>Ariela Levin</Name>
    <Email>ariela.levin@emailgame.com</Email>
    <Level>Intermediate</Level>
    <Cost>153</Cost>
  </Engineer>
  <Engineer>
    <Id>357604082</Id>
    <Name>Dina Klein</Name>
    <Email>dina.klein@emailgame.com</Email>
    <Level>Expert</Level>
    <Cost>291</Cost>
  </Engineer>
  <Engineer>
    <Id>353641111</Id>
    <Name>Shira Israelof</Name>
    <Email>shira.israelof@emailgame.com</Email>
    <Level>AdvancedBeginner</Level>
    <Cost>98</Cost>
  </Engineer>
  <Engineer>
    <Id>250372757</Id>
    <Name>Dani Levi</Name>
    <Email>dani.levi@emailgame.com</Email>
    <Level>Intermediate</Level>
    <Cost>80</Cost>
  </Engineer>
  <Engineer>
    <Id>123456789</Id>
    <Name>Eliezer El</Name>
    <Email>Eliezer@gmail.com</Email>
    <Level>Intermediate</Level>
    <Cost>300</Cost>
  </Engineer>
  <Engineer>
    <Id>987654321</Id>
    <Name>Shira Kehalani</Name>
    <Email>shira.ka017@gmail.com</Email>
    <Level>Advanced</Level>
    <Cost>301</Cost>
  </Engineer>
  <Engineer>
    <Id>654567898</Id>
    <Name>Tamar Chayat</Name>
    <Email>TAMARHAYAT1@gmail.com</Email>
    <Level>Advanced</Level>
    <Cost>301</Cost>
  </Engineer>
</ArrayOfEngineer>